Metadata-Version: 2.1
Name: vango
Version: 2.0.0
Summary: van go open api
Home-page: https://github.com/JanVee/VGPY
Author: JanVee
Author-email: 814107539@qq.com
License: MIT Licence
Keywords: vango,VGPY
Platform: any
